servicenow_browser_use/README.md
servicenow_browser_use/__init__.py
servicenow_browser_use/generate_selenium_from_recording.py
servicenow_browser_use/logging_config.py
servicenow_browser_use/selenium_generator.py
servicenow_browser_use/utils.py
servicenow_browser_use/agent/prompts.py
servicenow_browser_use/agent/service.py
servicenow_browser_use/agent/tests.py
servicenow_browser_use/agent/views.py
servicenow_browser_use/agent/message_manager/service.py
servicenow_browser_use/agent/message_manager/tests.py
servicenow_browser_use/agent/message_manager/views.py
servicenow_browser_use/browser/__init__.py
servicenow_browser_use/browser/browser.py
servicenow_browser_use/browser/browser_controller.py
servicenow_browser_use/browser/context.py
servicenow_browser_use/browser/recording_manager.py
servicenow_browser_use/browser/selenium_recorder.py
servicenow_browser_use/browser/shadow_dom.py
servicenow_browser_use/browser/streamlined_recorder.py
servicenow_browser_use/browser/views.py
servicenow_browser_use/browser/tests/screenshot_test.py
servicenow_browser_use/browser/tests/test_clicks.py
servicenow_browser_use/controller/service.py
servicenow_browser_use/controller/views.py
servicenow_browser_use/controller/registry/service.py
servicenow_browser_use/controller/registry/views.py
servicenow_browser_use/dom/__init__.py
servicenow_browser_use/dom/buildDomTree.js
servicenow_browser_use/dom/service.py
servicenow_browser_use/dom/views.py
servicenow_browser_use/dom/history_tree_processor/service.py
servicenow_browser_use/dom/history_tree_processor/view.py
servicenow_browser_use/dom/tests/extraction_test.py
servicenow_browser_use/dom/tests/process_dom_test.py
servicenow_browser_use/telemetry/service.py
servicenow_browser_use/telemetry/views.py
servicenow_browser_use-0.1.12.dist-info/METADATA
servicenow_browser_use-0.1.12.dist-info/WHEEL
servicenow_browser_use-0.1.12.dist-info/licenses/LICENSE
servicenow_browser_use-0.1.12.dist-info/RECORD
