Metadata-Version: 2.4
Name: servicenow-browser-use
Version: 0.1.12
Summary: A Python library for automating ServiceNow browser interactions
Project-URL: Homepage, https://github.com/joshita-das/servicenow-browser-use
Project-URL: Repository, https://github.com/joshita-das/servicenow-browser-use.git
Project-URL: Documentation, https://github.com/joshita-das/servicenow-browser-use#readme
Author-email: Joshita Das <joshita.das@servicenow.com>
License-Expression: MIT
License-File: LICENSE
Classifier: Development Status :: 3 - Alpha
Classifier: Intended Audience :: Developers
Classifier: License :: OSI Approved :: MIT License
Classifier: Programming Language :: Python :: 3
Classifier: Programming Language :: Python :: 3.8
Classifier: Programming Language :: Python :: 3.9
Classifier: Programming Language :: Python :: 3.10
Classifier: Programming Language :: Python :: 3.11
Requires-Python: >=3.8
Requires-Dist: beautifulsoup4>=4.13.3
Requires-Dist: langchain-anthropic>=0.1.1
Requires-Dist: langchain-openai>=0.3.1
Requires-Dist: lmnr>=0.4.66
Requires-Dist: maincontentextractor>=0.0.4
Requires-Dist: opentelemetry-api>=1.31.1
Requires-Dist: opentelemetry-exporter-otlp-proto-common>=1.31.1
Requires-Dist: opentelemetry-exporter-otlp-proto-grpc>=1.31.1
Requires-Dist: opentelemetry-exporter-otlp-proto-http>=1.31.1
Requires-Dist: opentelemetry-instrumentation-langchain>=0.38.12
Requires-Dist: opentelemetry-instrumentation-requests>=0.52b1
Requires-Dist: opentelemetry-instrumentation-sqlalchemy>=0.52b1
Requires-Dist: opentelemetry-instrumentation-threading>=0.52b1
Requires-Dist: opentelemetry-instrumentation-urllib3>=0.52b1
Requires-Dist: opentelemetry-instrumentation>=0.52b1
Requires-Dist: opentelemetry-proto>=1.31.1
Requires-Dist: opentelemetry-sdk>=1.31.1
Requires-Dist: opentelemetry-semantic-conventions-ai>=0.4.3
Requires-Dist: opentelemetry-semantic-conventions>=0.52b1
Requires-Dist: opentelemetry-util-http>=0.52b1
Requires-Dist: pillow>=11.1.0
Requires-Dist: playwright>=1.51.0
Requires-Dist: posthog>=3.21.0
Requires-Dist: pydantic>=2.10.6
Requires-Dist: python-dotenv>=1.0.1
Requires-Dist: requests>=2.32.3
Requires-Dist: selenium>=4.30.0
